pydomdisco-0.4.4.dist-info/METADATA
pydomdisco-0.4.4.dist-info/WHEEL
pydomdisco/pydomdisco.pyi
pydomdisco/__init__.py
pydomdisco/root_tld_to_nameservers_ips.pkl
pydomdisco/psl_tlds.pkl
pydomdisco/pydomdisco.cpython-310-darwin.so
pydomdisco-0.4.4.dist-info/RECORD
