Metadata-Version: 2.1
Name: pydomdisco
Version: 0.4.4
Classifier: License :: OSI Approved :: MIT License
Classifier: Operating System :: MacOS
Classifier: Operating System :: Microsoft
Classifier: Operating System :: POSIX :: Linux
Classifier: Programming Language :: Python :: 3.7
Classifier: Programming Language :: Python :: 3.8
Classifier: Programming Language :: Python :: 3.9
Classifier: Programming Language :: Python :: 3.10
Classifier: Programming Language :: Python :: 3.11
Classifier: Programming Language :: Rust
Summary: A fast async domain discovery tool written in Rust
Keywords: domain,discovery,dns,authoritative,resolver,rust,async,pyo3
Home-Page: https://github.com/intsights/pydomdisco
Author: Gal Ben David
Author-email: gal@intsights.com
License: MIT License
Requires-Python: >=3.7
Project-URL: Source Code, https://github.com/intsights/pydomdisco
